call_center_tools/__init__.py
call_center_tools/erlang.py
call_center_tools/staffing.py
call_center_tools-1.0.0.dist-info/LICENSE
call_center_tools-1.0.0.dist-info/METADATA
call_center_tools-1.0.0.dist-info/WHEEL
call_center_tools-1.0.0.dist-info/top_level.txt
call_center_tools-1.0.0.dist-info/RECORD
