Metadata-Version: 2.2
Name: call-center-tools
Version: 1.0.0
Summary: Tools for call center staffing calculations
Author-email: Ivan Perehiniak <iv.perehinik@gmail.com>
Project-URL: Homepage, https://github.com/perehinik/call-center-tools
Project-URL: Issues, https://github.com/perehinik/call-center-tools/issues
Classifier: Programming Language :: Python :: 3
Classifier: Operating System :: OS Independent
Classifier: License :: OSI Approved :: MIT License
Requires-Python: >=3.8
License-File: LICENSE
